Metadata-Version: 2.1
Name: alg0xxx
Version: 0.0
Summary: alg0xxx
Author-email: applepro285@gmail.com
